<ti:work xmlns:ti="http://chs.harvard.edu/xmlns/cts" groupUrn="urn:cts:latty:payr01" urn="urn:cts:latty:payr01.latty2648970" xml:lang="lat">
  <ti:title xml:lang="lat">Apologia inter Sarcophibum et Sarcophilum cum Crisi Theophili Veronensis</ti:title>
  <ti:edition workUrn="urn:cts:latty:payr01.latty2648970" urn="urn:cts:latty:payr01.latty2648970.latty-lat1:">
    <ti:label xml:lang="lat">Apologia inter Sarcophibum et Sarcophilum cum Crisi Theophili Veronensis, seu
                    Discursus Rationalis de Praecepto Ecclesiastico Jejunii et Abstinentiae, versio
                    electronica</ti:label>
    <ti:description xml:lang="eng">CTS compliant Tyrolean Neo-Latin texts</ti:description>
  </ti:edition>
</ti:work>